timedate/__init__.py
advanced_timedate-3.0.5.dist-info/METADATA
advanced_timedate-3.0.5.dist-info/WHEEL
advanced_timedate-3.0.5.dist-info/licenses/LICENSE
advanced_timedate-3.0.5.dist-info/RECORD
