Metadata-Version: 2.1
Name: advanced-timedate
Version: 3.0.5
Summary: Advanced date and time management library.
Project-URL: Homepage, https://github.com/LassaInora/Timedate
Project-URL: Bug Tracker, https://github.com/LassaInora/Timedate/issues
Author-email: Axelle Viandier <lassainora@lassainora.fr>
License-File: LICENSE
Classifier: License :: OSI Approved :: GNU General Public License v3 (GPLv3)
Classifier: Operating System :: OS Independent
Classifier: Programming Language :: Python :: 3
Requires-Python: >=3.6
